pyawsbillinginfo/__init__.py
pyawsbillinginfo/aws_billing_data.csv
pyawsbillinginfo/pyawsbillinginfo.py
pyawsbillinginfo-0.1.7.dist-info/LICENSE
pyawsbillinginfo-0.1.7.dist-info/METADATA
pyawsbillinginfo-0.1.7.dist-info/WHEEL
pyawsbillinginfo-0.1.7.dist-info/entry_points.txt
pyawsbillinginfo-0.1.7.dist-info/RECORD
