Metadata-Version: 2.1
Name: pyawsbillinginfo
Version: 0.1.7
Summary: A CLI for retrieving AWS Billing info
License: Apache-2.0
Author: Joe Drumgoole
Author-email: joe@joedrumgoole.com
Requires-Python: >=3.10,<4.0
Classifier: License :: OSI Approved :: Apache Software License
Classifier: Programming Language :: Python :: 3
Classifier: Programming Language :: Python :: 3.10
Classifier: Programming Language :: Python :: 3.11
Classifier: Programming Language :: Python :: 3.12
Requires-Dist: boto3 (>=1.35.3,<2.0.0)
Requires-Dist: configargparse (>=1.7,<2.0)
